openapi_burrito/__init__.py
openapi_burrito/cli.py
openapi_burrito/generator.py
openapi_burrito/preview.py
openapi_burrito/utils.py
openapi_burrito/parser/lookup.py
openapi_burrito/parser/models.py
openapi_burrito/parser/operation.py
openapi_burrito/parser/sanitize.py
openapi_burrito/parser/schema.py
openapi_burrito/parser/types.py
openapi_burrito/templates/__init__.py.jinja2
openapi_burrito/templates/client.py.jinja2
openapi_burrito/templates/models.py.jinja2
openapi_burrito/templates/pyproject.toml.jinja2
openapi_burrito-0.1.1.dist-info/METADATA
openapi_burrito-0.1.1.dist-info/WHEEL
openapi_burrito-0.1.1.dist-info/entry_points.txt
openapi_burrito-0.1.1.dist-info/licenses/LICENSE
openapi_burrito-0.1.1.dist-info/RECORD
