Metadata-Version: 2.4
Name: openapi-burrito
Version: 0.1.1
Summary: A lightweight CLI tool to generate a type-safe Python client from an OpenAPI specification.
Project-URL: Homepage, https://github.com/simon-lund/openapi-burrito
Project-URL: Documentation, https://github.com/simon-lund/openapi-burrito#readme
Project-URL: Repository, https://github.com/simon-lund/openapi-burrito.git
Project-URL: Issues, https://github.com/simon-lund/openapi-burrito/issues
Author-email: Simon Lund <simon.lund@lmu.de>
License: MIT
License-File: LICENSE
Keywords: code-generation,httpx,openapi,openapi-fetch,sdk-generator,swagger,type-safe
Classifier: Intended Audience :: Developers
Classifier: License :: OSI Approved :: MIT License
Classifier: Operating System :: OS Independent
Classifier: Programming Language :: Python :: 3.12
Classifier: Programming Language :: Python :: 3.13
Classifier: Programming Language :: Python :: 3.14
Requires-Python: >=3.12
Requires-Dist: httpx~=0.28.1
Requires-Dist: jinja2~=3.1.6
Requires-Dist: openapi-spec-validator~=0.7.2
Requires-Dist: prance[osv]~=25.4.8.0
Requires-Dist: typer~=0.21.0
Provides-Extra: preview
Requires-Dist: fastapi[standard]~=0.128.0; extra == 'preview'
